tiny_retry/__init__.py
tiny_retry/retry.py
tiny_retry_gw-0.2.1.dist-info/licenses/LICENSE
tiny_retry_gw-0.2.1.dist-info/METADATA
tiny_retry_gw-0.2.1.dist-info/WHEEL
tiny_retry_gw-0.2.1.dist-info/top_level.txt
tiny_retry_gw-0.2.1.dist-info/RECORD
