Metadata-Version: 2.4
Name: tiny-retry-gw
Version: 0.2.1
Summary: A tiny retry helper for synchronous Python code.
Author: Gatoware
License:                                  Apache License
Project-URL: Homepage, https://github.com/Gatoware-6310/tiny-retry
Classifier: License :: OSI Approved :: Apache Software License
Classifier: Programming Language :: Python :: 3
Classifier: Programming Language :: Python :: 3 :: Only
Classifier: Operating System :: OS Independent
Requires-Python: >=3.8
License-File: LICENSE
Dynamic: license-file
